{
    "_id": 221,
    "evoLine": [
        [
            {
                "id": 624,
                "name": "Pawniard",
                "type": {
                    "one": "Dark",
                    "two": "Steel"
                }
            },
            {
                "id": 625,
                "name": "Bisharp",
                "type": {
                    "one": "Dark",
                    "two": "Steel"
                },
                "how": "Level 52"
            },
            {
                "id": 983,
                "name": "Kingambit",
                "type": {
                    "one": "Dark",
                    "two": "Steel"
                },
                "how": "Defeat 3 Bisharp that are holding Leader's Crest"
            }
        ]
    ]
}
